README.rst
setup.cfg
setup.py
consciousnet/__init__.py
consciousnet/info.py
consciousnet.egg-info/PKG-INFO
consciousnet.egg-info/SOURCES.txt
consciousnet.egg-info/dependency_links.txt
consciousnet.egg-info/requires.txt
consciousnet.egg-info/top_level.txt
consciousnet/augmentation/__init__.py
consciousnet/augmentation/barlowtwins.py
consciousnet/losses/__init__.py
consciousnet/losses/gmvae.py
consciousnet/losses/tdvae.py
consciousnet/models/__init__.py
consciousnet/models/barlowtwins.py
consciousnet/models/deepcluster_tmp.py
consciousnet/models/distributions.py
consciousnet/models/gmvae.py
consciousnet/models/tdvae.py
consciousnet/optim/__init__.py
consciousnet/optim/lars.py
consciousnet/plotting/__init__.py
consciousnet/plotting/patterns.py
consciousnet/plotting/reconstruction.py
consciousnet/sampler/__init__.py
consciousnet/sampler/uniform.py