Metadata-Version: 1.1
Name: consciousnet
Version: 0.0.0
Summary: 
